angry_purple_tiger/__init__.py
angry_purple_tiger/adjectives.py
angry_purple_tiger/angry_purple_tiger.py
angry_purple_tiger/animals.py
angry_purple_tiger/colors.py
angry_purple_tiger/compress.py
LICENSE
angry_purple_tiger-0.2.0.dist-info/LICENSE
angry_purple_tiger-0.2.0.dist-info/WHEEL
angry_purple_tiger-0.2.0.dist-info/METADATA
angry_purple_tiger-0.2.0.dist-info/RECORD
