Metadata-Version: 2.1
Name: angry-purple-tiger
Version: 0.2.0
Summary: Animal-based hash digests for humans
Home-page: https://github.com/evandiewald/angry-purple-tiger-py
License: Apache-2.0
Author: Evan Diewald
Author-email: evandiewald@gmail.com
Requires-Python: >=3.7,<4.0
Classifier: License :: OSI Approved :: Apache Software License
Classifier: Programming Language :: Python :: 3
Classifier: Programming Language :: Python :: 3.10
Classifier: Programming Language :: Python :: 3.7
Classifier: Programming Language :: Python :: 3.8
Classifier: Programming Language :: Python :: 3.9
Project-URL: Repository, https://github.com/evandiewald/angry-purple-tiger-py
